my_data_preprocessor_mz/__init__.py
my_data_preprocessor_mz/categorical_encoder.py
my_data_preprocessor_mz/data_type_converter.py
my_data_preprocessor_mz/datetime_handler.py
my_data_preprocessor_mz/missing_value_handler.py
my_data_preprocessor_mz/outlier_handler.py
my_data_preprocessor_mz/scaler.py
my_data_preprocessor_mz/text_cleaner.py
tests/__init__.py
tests/main.py
tests/test_data_type_converter.py
tests/test_datetime_handler.py
tests/test_missing_value_handler.py
tests/test_outlier_handler.py
tests/test_scaler.py
my_data_preprocessor_mz-0.3.0.dist-info/LICENSE.txt
my_data_preprocessor_mz-0.3.0.dist-info/METADATA
my_data_preprocessor_mz-0.3.0.dist-info/WHEEL
my_data_preprocessor_mz-0.3.0.dist-info/top_level.txt
my_data_preprocessor_mz-0.3.0.dist-info/RECORD
