Metadata-Version: 2.1
Name: my_data_preprocessor_mz
Version: 0.3.0
Summary: A comprehensive data preprocessing library for data engineering tasks
Home-page: https://github.com/meyvadem/my_data_preprocessor
Author: Merve Demir, Zeynep Dagtekin
Author-email: zeynep.dagtekin@stu.fsm.edu.tr
License: MIT
Classifier: Programming Language :: Python :: 3
Classifier: License :: OSI Approved :: MIT License
Classifier: Operating System :: OS Independent
Requires-Python: >=3.6
License-File: LICENSE.txt
Requires-Dist: pandas
Requires-Dist: numpy
Requires-Dist: nltk
Requires-Dist: scikit-learn
